nvidiacheck/README.MD
nvidiacheck/__init__.py
nvidiacheck/requirements.txt
nvidiacheck/thirdparty.json
nvidiacheck-0.10.dist-info/LICENSE.rst
nvidiacheck-0.10.dist-info/METADATA
nvidiacheck-0.10.dist-info/WHEEL
nvidiacheck-0.10.dist-info/top_level.txt
nvidiacheck-0.10.dist-info/RECORD
