Metadata-Version: 2.1
Name: nvidiacheck
Version: 0.10
Summary: Monitors NVIDIA GPU information and log the data into a pandas DataFrame - Windows only.
Home-page: https://github.com/hansalemaos/nvidiacheck
Author: Johannes Fischer
Author-email: aulasparticularesdealemaosp@gmail.com
License: MIT
Keywords: nvidia,cuda,log
Classifier: Development Status :: 4 - Beta
Classifier: Programming Language :: Python :: 3 :: Only
Classifier: Programming Language :: Python :: 3.10
Classifier: Topic :: Software Development :: Libraries :: Python Modules
Classifier: Topic :: Utilities
License-File: LICENSE.rst
Requires-Dist: pandas
